matiz/__init__.py
matiz/_common.py
matiz/_contain.py
matiz/_exceptions.py
matiz/_fields.py
matiz/_fields_obsolete.py
matiz/_serializ.py
matiz/_valid.py
matiz/_yamliz.py
tests/__init__.py
tests/conftest.py
tests/pyitef-l2tpv3.py
tests/some_test_defs.py
tests/test_able.py
tests/test_concept.py
tests/test_containable.py
tests/test_fields.py
tests/test_zyang.py
matiz-0.1.4.dist-info/LICENSE
matiz-0.1.4.dist-info/METADATA
matiz-0.1.4.dist-info/WHEEL
matiz-0.1.4.dist-info/top_level.txt
matiz-0.1.4.dist-info/RECORD
