Metadata-Version: 2.1
Name: matiz
Version: 0.1.4
Summary: Serves modern approach to data structures definition - with a minimal boilerplate.
Home-page: https://gitlab.com/kamichal/yamliz
Author: Michał Kaczmarczyk
Author-email: michal.s.kaczmarczyk@gmail.com
License: UNKNOWN
Keywords: dataclasses,dataclass,yang,validation,yaml,raw,binary,encoding,decoding
Platform: UNKNOWN
Classifier: Development Status :: 3 - Alpha
Classifier: Programming Language :: Python
Classifier: Programming Language :: Python :: 3
Classifier: Programming Language :: Python :: 3.7
Classifier: Operating System :: OS Independent
Requires-Python: >=3.7
Requires-Dist: pyyaml (==5.*)
